{"inkVersion":21,"root":[["\n",{"->":"main"},["done",{"#f":5,"#n":"g-0"}],null],"done",{"main":["ev",{"VAR?":"raine_interactions"},"str","^","/str","==","/ev",[{"->":".^.b","c":true},{"b":["\n",{"->":"log1"},{"->":"main.8"},null]}],"nop","\n","ev",{"VAR?":"raine_interactions"},1,"==","/ev",[{"->":".^.b","c":true},{"b":["\n",{"->":"log2"},{"->":"main.16"},null]}],"nop","\n","ev",{"VAR?":"raine_interactions"},2,">=","/ev",[{"->":".^.b","c":true},{"b":["\n",{"->":"log3"},{"->":"main.24"},null]}],"nop","\n",{"#f":1}],"log1":["^[Raine] Who are you? You can see me? ","#","^speaker: Raine","/#","\n","^[Addison] I can. Who are you? ","#","^speaker: Addison","/#","\n","^[Raine] I’m Raine! I’m seven years olddd!! ","#","^speaker: Raine","/#","\n","^[Addison] Oh, I’m Addison. Nice to meet you. Why are you here? ","#","^speaker: Addison","/#","\n","^[Raine] I’m waiting for mama to pick me up to go back home. Who’s that? ","#","^speaker: Raine","/#","\n","^[Mom] Hi dearie! I’m Addison’s mom. Where’s your mom? ","#","^speaker: Mom","/#","\n","^[Raine] I’m not sure… ","#","^speaker: Raine","/#","\n","^[Raine] I just know one day I was having a tea party here, but my friend— Mr. Teetee— he almost fell off the roof, so I tried to catch him. ","#","^speaker: Raine","/#","\n","^[Raine] I don’t remember what happened, but I found myself floating around and glowing! ","#","^speaker: Raine","/#","\n","^[Mom] Oh dear… ","#","^speaker: Mom","/#","\n","^[Raine] After I got used to floating around, I tried to look for mama, but I couldn't find her. ","#","^speaker: Raine","/#","\n","^[Raine] Then, I remembered that she said to always stay where I am so she can find me! ","#","^speaker: Raine","/#","\n","^[Raine] Have you seen mama? ","#","^speaker: Raine","/#","\n","^[Mom] I don’t think I have, darling. ","#","^speaker: Mom","/#","\n","^[Raine] Oh... That’s okay. Thanks anyway! I’ll keep waiting for her! ","#","^speaker: Raine","/#","\n","ev",1,"/ev",{"VAR=":"times_interacted","re":true},"ev",{"VAR?":"times_interacted"},"/ev",{"VAR=":"raine_interactions","re":true},"done",{"#f":1}],"log2":["^[Raine] I miss mama… ","#","^speaker: Raine","/#","\n","^[Raine] How come your mama is floating and glowing like me? ","#","^speaker: Raine","/#","\n","^[Addison] Hm… I think you must have drank tea with magical abilities. Maybe your mama will drink the same tea as you and float and glow like you. ","#","^speaker: Addison","/#","\n","^[Raine] Really? I want that! I hope she’ll drink the magical tea so I can see her clearly! It’s hard to find her when she’s not floaty and glowy. ","#","^speaker: Raine","/#","\n","ev",2,"/ev",{"VAR=":"times_interacted","re":true},"ev",{"VAR?":"times_interacted"},"/ev",{"VAR=":"raine_interactions","re":true},"done",{"#f":1}],"log3":["^[Raine] Mr. Teetee, don’t drink so much tea! You’ll have to pee again!! ","#","^speaker: Raine","/#","\n","done",{"#f":1}],"global decl":["ev","str","^","/str",{"VAR=":"number_chosen"},"str","^","/str",{"VAR=":"dog_interactions"},"str","^","/str",{"VAR=":"gma_interactions"},"str","^","/str",{"VAR=":"raine_interactions"},"str","^en","/str",{"VAR=":"localeID"},0,{"VAR=":"times_interacted"},"/ev","end",null],"#f":1}],"listDefs":{}}