{"inkVersion":21,"root":[["\n","ev",{"VAR?":"localeID"},"/ev",{"VAR=":"currentLocale","re":true},["ev",{"VAR?":"currentLocale"},"str","^en","/str","==","/ev",{"->":".^.b","c":true},{"b":["\n",{"->":"main_en"},"done",{"->":"0.8"},null]}],["ev",{"VAR?":"currentLocale"},"str","^fa","/str","==","/ev",{"->":".^.b","c":true},{"b":["\n",{"->":"main_fa"},"done",{"->":"0.8"},null]}],["ev",{"VAR?":"currentLocale"},"str","^ja","/str","==","/ev",{"->":".^.b","c":true},{"b":["\n",{"->":"main_ja"},"done",{"->":"0.8"},null]}],"nop","\n",["done",{"#f":5,"#n":"g-0"}],null],"done",{"main_en":[["^Who's there? ","#","^speaker: Addison","/#","\n","^<i>I scratch my eyes in disbelief. Although I couldn't believe it, the one standing right in front of me is ...</i> ","#","^speaker: Addison","/#","\n","^...Mom??? ","#","^speaker: Addison","/#","\n","^What the — ? ","#","^speaker: Addison","/#","\n","^Calm down, Addison — it's me! ","#","^speaker: Mom","/#","\n","^<i>All I can do is stand there, stunned in shock. Is this real?</i>","#","^speaker: Addison","/#","\n","^No, that can't be right ...I must be imagining things, I'm still in a dream — yeah, that's it!","\n","^I'm still dreaming. I should pinch myself to wake up, isn't that how it works? ","#","^speaker: Addison","/#","\n","^CALM DOWN! ","#","^speaker: Mom","/#","\n","^... ","#","^speaker: Addison","/#","\n","^... ","#","^speaker: Addison","/#","\n","^... ","#","^speaker: Addison","/#","\n","^It's going to be alright, sweetie. ","#","^speaker: Mom","/#","\n","^I've missed you so much ... ","#","^speaker: Addison","/#","\n","^I've missed you too, Addison. ","#","^speaker: Mom","/#","\n","^Once I died, I've always been by your side. But you weren't able to see me ... ","#","^speaker: Mom","/#","\n","^...until now. ","#","^speaker: Mom","/#","\n","^Why can I see you now Mom? ","#","^speaker: Addison","/#","\n","^Why now? ","#","^speaker: Addison","/#","\n","^I can explain what's going on.  ","#","^speaker: Mom","/#","\n","^Another ghost had told me that I'm stuck in a limbo spirit world. ","#","^speaker: Mom","/#","\n","^According to them, I can't move on until I collect enough <color=#aefff1>“special” objects</color>.  ","#","^speaker: Mom","/#","\n","^If I don't find them soon, I'll evaporate into dust and will disappear from the face of this world. ","#","^speaker: Mom","/#","\n","^The only issue is ...I can't touch anything. I just go through everything. ","#","^speaker: Mom","/#","\n","^Do you think you can help me, sweetie? ","#","^speaker: Mom","/#","\n","ev","str","^I guess ...","/str","/ev",{"*":".^.c-0","flg":4},"ev","str","^Of course!","/str","/ev",{"*":".^.c-1","flg":4},{"c-0":["\n","^I know things didn't end well for us, and I'm sorry for that. Let's go on one more journey together, yeah? ","#","^speaker: Mom","/#","\n","ev",false,"/ev",{"VAR=":"ready","re":true},"ev",{"VAR?":"ready"},"/ev",{"VAR=":"is_ready","re":true},"done",{"#f":5}],"c-1":["\n","^Thank you, sweetie. Let's go get ready. ","#","^speaker: Mom","/#","\n","ev",true,"/ev",{"VAR=":"ready","re":true},"ev",{"VAR?":"ready"},"/ev",{"VAR=":"is_ready","re":true},"done",{"#f":5}]}],{"#f":1}],"main_fa":[["#","^speaker: ادیسون","/#","^کی اونجاست؟","\n","^...چشامو چند بار باز و بسته کردم ولی هنوز باورم نمیشه. اونی که جلوم وایساده","\n","^...مامان؟","\n","^یعنی که چی؟ مگه میشه؟","\n","#","^speaker:  مامان","/#","^!آروم باش ادیسون، منم","\n","#","^speaker: ادیسون","/#","^از هیجان خشکم زده بود، باورم نمیشه که اینجا پیشمه! این واقعیه؟","\n","^.نه بابا دارم توهم میزنم… دوباره مثله اینکه فشارم افتاده… اینا همش یه خوابه","\n","#","^speaker:  مامان","/#","^آروم باش عزیزم","\n","^.همه چی درست میشه عزیزم تو یکم آروم شو فقط","\n","#","^speaker: ادیسون","/#","^.ماااامااااان… دلم برات یه ذره شده بود","\n","#","^speaker:  مامان","/#","^.منم همینطور قشنگم","\n","^...از وقتی این اتفاق افتاده من از پیست تکون نخوردم، ولی تو منو نمیتونستی ببینی","\n","^...تا امروز","\n","#","^speaker: ادیسون","/#","^الان چطوری میتونم ببینمت پس؟","\n","^چرا امروز؟","\n","#","^speaker:  مامان","/#","^بیا برات توضیح بدم عزیزم","\n","^یه روحه دیگه ای بهم گفت که من تو این دنیا گیر کردم. مثله اینکه، من تا وقتی که همه چیزایی که لازم دارم رو","\n","^.پیدا نکنم تو این دنیا گیرم","\n","^اگه تا چند وقت دیگه پیداشون نکنم، روح ام کلاً از همه جا پاک میشه و دیگه تو هیچ دنیایی نمی‌تونم زندگی کنم.","\n","^.تنها مشکلم اینه که نمیتونم هیچ چی رو لمس کنم","\n","^تو میتونی کمکم کنی خوشگلم؟","\n","#","^speaker: ادیسون","/#","ev","str","^...اگه بتونم","/str","/ev",{"*":".^.c-0","flg":4},"ev","str","^حتما‌ً","/str","/ev",{"*":".^.c-1","flg":4},{"c-0":["\n","#","^speaker:  مامان","/#","^میدونم که آخرین باری که همو دیدیم خاطره خوبی برات نبوده و من متاسفم برای اون شب. بیا واسه آخرین بار","\n","^.هم که شده باهم این مشکل رو رفع کنیم","\n","ev",false,"/ev",{"VAR=":"ready","re":true},"ev",{"VAR?":"ready"},"/ev",{"VAR=":"is_ready","re":true},"done",{"#f":5}],"c-1":["\n","#","^speaker:  مامان","/#","^!مرسی عزیزم، پاشو بریم","\n","ev",true,"/ev",{"VAR=":"ready","re":true},"ev",{"VAR?":"ready"},"/ev",{"VAR=":"is_ready","re":true},"done","done",{"#f":5}]}],{"#f":1}],"main_ja":[["#","^speaker:「アディソン」","/#","^「誰か？」","\n","^目を描きます。信じられないけど、その私の前に立っている存在は。。。","\n","^「。。。母？」","\n","^「なんだ、これー！」","\n","#","^speaker:「母」","/#","^「落ち着け、アディソン！」","\n","#","^speaker:「アディソン」","/#","^ショックで、ただそこに立っていることしかできない。これは現実か？","\n","^「いやいや、そんな、。。。気のせいだろう、まだ夢見ているのだろうね。。。」","\n","^「そうよ！まだ夢見てる。目を覚めるために自分をつねらなけないだろう...。そういうものだろう？」","\n","#","^speaker:「母」","/#","^「落ち着け！」","\n","^。。。","\n","^。。。","\n","^「大丈夫だよ、アディソン。」","\n","#","^speaker:「アディソン」","/#","^「会いたかったよう。。。」","\n","#","^speaker:「母」","/#","^「私も、アディソンに会いたかよ。。。」","\n","^「私が亡くなり、ずっと一緒でしたよ。でも、あんたは私を見えませんでした。。。」","\n","^「。。。今までけど。」","\n","#","^speaker:「アディソン」","/#","^「どうして今、母に見えるの？」","\n","^「どうして。。。今。。。」","\n","#","^speaker:「母」","/#","^「説明しよう。」","\n","^「他のゴーストから、私は今リンボー霊界から出せないと言われました。出せるのために、<color=#aefff1>特別なも</color>のを集めます。」","\n","^「もうすぐ探しないと、この世界からきえます。」","\n","^「ですが、私は何も触りません。全て通り抜ける。」","\n","^「手伝ってくれませんか、アディソン？」","\n","#","^speaker:「アディソン」","/#","ev","str","^まあ。。","/str","/ev",{"*":".^.c-0","flg":4},"ev","str","^もちろん！","/str","/ev",{"*":".^.c-1","flg":4},{"c-0":["\n","#","^speaker: 母","/#","^「うまくいかなかった、ごめん。もう一つ一緒に旅に行こうね？」","\n","ev",false,"/ev",{"VAR=":"ready","re":true},"ev",{"VAR?":"ready"},"/ev",{"VAR=":"is_ready","re":true},"done",{"#f":5}],"c-1":["\n","#","^speaker: 「母","/#","^「ありがとう、アディソン。さあ、準備にしよう。」 」","\n","ev",true,"/ev",{"VAR=":"ready","re":true},"ev",{"VAR?":"ready"},"/ev",{"VAR=":"is_ready","re":true},"done","end",{"#f":5}]}],{"#f":1}],"global decl":["ev","str","^","/str",{"VAR=":"localeID"},false,{"VAR=":"is_ready"},"str","^","/str",{"VAR=":"number_chosen"},"str","^","/str",{"VAR=":"dog_interactions"},"str","^","/str",{"VAR=":"gma_interactions"},false,{"VAR=":"fridgeInteraction"},false,{"VAR=":"livingInteraction"},"str","^","/str",{"VAR=":"raine_interactions"},"str","^","/str",{"VAR=":"abby_interactions"},"str","^","/str",{"VAR=":"larry_interactions"},"str","^","/str",{"VAR=":"rowan_interactions"},"str","^","/str",{"VAR=":"key_obtained"},"str","^","/str",{"VAR=":"depressionFirstDialogue"},"str","^","/str",{"VAR=":"depressionRoofDialogue"},"str","^","/str",{"VAR=":"depressionMiddleDialogue"},0,{"VAR=":"test_variable"},"str","^","/str",{"VAR=":"currentLocale"},false,{"VAR=":"ready"},"/ev","end",null],"#f":1}],"listDefs":{}}